virtualscanner/__init__.py
virtualscanner/utest_gui.py
virtualscanner/coms/__init__.py
virtualscanner/coms/coms_ui/GUI_test_functions.py
virtualscanner/coms/coms_ui/GUI_utest.py
virtualscanner/coms/coms_ui/__init__.py
virtualscanner/coms/coms_ui/coms_server_flask.py
virtualscanner/coms/coms_ui/geckodriver.log
virtualscanner/coms/coms_ui/standard_mode_GUI_selenium.py
virtualscanner/coms/coms_ui/utest_coms_ui.py
virtualscanner/coms/coms_ui/__pycache__/GUI_test_functions.cpython-36.pyc
virtualscanner/coms/coms_ui/__pycache__/__init__.cpython-310.pyc
virtualscanner/coms/coms_ui/__pycache__/__init__.cpython-36.pyc
virtualscanner/coms/coms_ui/__pycache__/__init__.cpython-39.pyc
virtualscanner/coms/coms_ui/__pycache__/coms_server_flask.cpython-36.pyc
virtualscanner/coms/coms_ui/__pycache__/coms_server_flask_alt.cpython-36.pyc
virtualscanner/coms/coms_ui/__pycache__/routes_research.cpython-39.pyc
virtualscanner/coms/coms_ui/__pycache__/utest_GUI_functions.cpython-36.pyc
virtualscanner/coms/coms_ui/__pycache__/utest_coms_ui.cpython-310.pyc
virtualscanner/coms/coms_ui/firefox_driver/geckodriver_windows.exe
virtualscanner/coms/coms_ui/static/__init__.py
virtualscanner/coms/coms_ui/static/acquire_func.js
virtualscanner/coms/coms_ui/static/acquire_style.css
virtualscanner/coms/coms_ui/static/advanced_mode_style.css
virtualscanner/coms/coms_ui/static/analyze_func.js
virtualscanner/coms/coms_ui/static/analyze_style.css
virtualscanner/coms/coms_ui/static/favicon.ico
virtualscanner/coms/coms_ui/static/form2Json.js
virtualscanner/coms/coms_ui/static/log_in_func.js
virtualscanner/coms/coms_ui/static/log_in_style.css
virtualscanner/coms/coms_ui/static/log_out_func.js
virtualscanner/coms/coms_ui/static/logo-blue-white-onlycrown.png
virtualscanner/coms/coms_ui/static/main_style.css
virtualscanner/coms/coms_ui/static/metric_imperial.js
virtualscanner/coms/coms_ui/static/phantomAutofill.js
virtualscanner/coms/coms_ui/static/recon_func.js
virtualscanner/coms/coms_ui/static/recon_style.css
virtual_scanner-2.0.0.post5.dist-info/LICENSE
virtual_scanner-2.0.0.post5.dist-info/METADATA
virtual_scanner-2.0.0.post5.dist-info/WHEEL
virtual_scanner-2.0.0.post5.dist-info/entry_points.txt
virtual_scanner-2.0.0.post5.dist-info/top_level.txt
virtual_scanner-2.0.0.post5.dist-info/RECORD
